rotter/__init__.py
rotter/main.py
rotter-0.0.1.dist-info/METADATA
rotter-0.0.1.dist-info/WHEEL
rotter-0.0.1.dist-info/entry_points.txt
rotter-0.0.1.dist-info/licenses/LICENSE
rotter-0.0.1.dist-info/RECORD
