Metadata-Version: 2.1
Name: rotter
Version: 0.0.1
Summary: Interactive python exercises
Project-URL: Homepage, https://github.com/hogeschool/rotter
Project-URL: Bug Tracker, https://github.com/hogeschool/rotter/issues
Author-email: Merijn Aktas <m.aktas@hr.nl>
License-File: LICENSE
Classifier: License :: OSI Approved :: MIT License
Classifier: Operating System :: OS Independent
Classifier: Programming Language :: Python :: 3
Requires-Python: >=3.7
